anki_deck_from_text/__init__.py
anki_deck_from_text/cli.py
anki_deck_from_text/generate_deck.py
anki_deck_from_text/models.py
anki_deck_from_text/parse_input.py
anki_deck_from_text-1.3.4.dist-info/LICENSE
anki_deck_from_text-1.3.4.dist-info/METADATA
anki_deck_from_text-1.3.4.dist-info/WHEEL
anki_deck_from_text-1.3.4.dist-info/entry_points.txt
anki_deck_from_text-1.3.4.dist-info/RECORD
