Metadata-Version: 2.1
Name: anki_deck_from_text
Version: 1.3.4
Summary: Generate an Anki deck from annotations on a text file
Author: Andre Macedo
Author-email: andre.lopes.macedo@gmail.com
Requires-Python: >=3.12,<4.0
Classifier: Programming Language :: Python :: 3
Classifier: Programming Language :: Python :: 3.12
Requires-Dist: chardet (>=5.2.0,<6.0.0)
Requires-Dist: click (>=8.1.7,<9.0.0)
Requires-Dist: genanki (>=0.13.1,<0.14.0)
